pytext/__init__.py
pytext_nlp_gpu-0.1.dist-info/LICENSE
pytext_nlp_gpu-0.1.dist-info/METADATA
pytext_nlp_gpu-0.1.dist-info/WHEEL
pytext_nlp_gpu-0.1.dist-info/top_level.txt
pytext_nlp_gpu-0.1.dist-info/RECORD
