Metadata-Version: 2.1
Name: pytext-nlp-gpu
Version: 0.1
Summary: pytorch modeling framework and model zoo for text models
Home-page: UNKNOWN
Author: Facebook
Author-email: UNKNOWN
License: BSD
Platform: UNKNOWN
